[
	{"roles":[
		{
			"rolesPic":"images/heilong.png"
		},
		{
			"introduce":"images/part3_heilong.png"
		},
		{"tafang":[
			{
				"title":[{"title1":"龙爪"},{"title2":"熔岩之地"},{"title3":"龙炮"},{"title4":"龙息"}]
			},
			{
			"info1":"普通攻击，黑龙女王的攻击，对小范围内的敌人造成2次魔法伤害",
			"info2":"被动技能，触发概率和技能触发值有关，对范围内的敌人造成3段魔法伤害",
			"info3":"主动技能，一层能量满时可以释放，黑龙聚集能量发出魔法球，对范围内的敌人造成大量魔法伤害",
			"info4":"主动技能，二层能量满时可以释放，黑龙飞上天空，对着地面无情的吐出火焰，对全屏的敌人造成7次魔法伤害",
			"img1":"images/heilong_1.png",
			"img2":"images/heilong_2.png",
			"img3":"images/heilong_3.png",
			"img4":"images/heilong_4.png"
			}
		]},
		{"duizhan":[
			{
				"title1":"黑龙的威严（主动）",
				"title2":"龙体（被动）"
			},
			{
			"info1":"震慑对方，造成150%伤害，使对方技能触发值增加30%，防御力降低40%，持续3回合",
			"info2":"受到的伤害降低33%",
			"img5":"images/heilong_1.png",
			"img6":"images/heilong_2.png"
			}		
		]},
		{"juexing":[
			{
				"img":"images/roles_heilong.png"				
			},
			{
				"imgOn":"images/roles_heilong_on.png"
			}
		]}
	]
	},
	{"roles":[
		{
			"rolesPic":"images/banrenma.png"
		},
		{
			"introduce":"images/part3_banrenma.png"
		},
		{"tafang":[
			{
				"title":[{"title1":"长毛投掷（普攻）"},{"title2":"马蹄践踏（被动）"},{"title3":"穿心长矛（小技能）"},{"title4":"碎心长矛（大技能）"}]
			},
			{
			"info1":"普通攻击，投掷出手中的长矛，造成物理伤害",
			"info2":"被动技能，触发概率和技能触发值有关，人立而起，用马蹄践踏对面，造成以自身为半径的物理伤害",
			"info3":"主动技能，一层能量满时可以释放，集气于长矛上，然后投掷出去，对直线上的所有敌人造成物理伤害",
			"info4":"主动技能，二层能量满时可以释放，蓄气于长矛上，然后投掷出去，对范围内的所有敌人造成大量物理伤害",
			"img1":"images/banrenma_1.png",
			"img2":"images/banrenma_2.png",
			"img3":"images/banrenma_3.png",
			"img4":"images/banrenma_4.png"
			}
		]},
		{"duizhan":[
			{
				"title1":"精灵标记（主动）",
				"title2":"射手精通（被动）"
			},
			{
			"info1":"造成120%伤害，同时标记目标，使目标受到伤害提高40%，持续2回合",
			"info2":"每次攻击使自己造成的伤害提高10%，持续1回合，最多可叠加5层",
			"img5":"images/banrenma_5.png",
			"img6":"images/banrenma_6.png"
			}		
		]},
		{"juexing":[
			{
				"img":"images/roles_banrenma.png"				
			}
		]}
	]
	}
	,
	{"roles":[
		{
			"rolesPic":"images/shizijun.png"
		},
		{
			"introduce":"images/part3_shizijun.png"
		},
		{"tafang":[
			{
				"title":[{"title1":"挥砍（普攻）"},{"title2":"盾牌猛击（被动）"},{"title3":"剑气斩（小技能）"},{"title4":"蓄气斩（大技能）"}]
			},
			{
			"info1":"普通攻击，快速的砍击，造成物理伤害",
			"info2":"被动技能，触发概率和技能触发值有关，将手中的盾牌飞出去再收回来，对沿途的敌人造成物理伤害",
			"info3":"主动技能，一层能量满时可以释放，集气于剑上，然后挥砍出去，对直线上的所有敌人造成物理伤害",
			"info4":"主动技能，二层能量满时可以释放，蓄气于剑上，然后挥砍出去，对直线上的所有敌人造成2次物理伤害",
			"img1":"images/shizijun_1.png",
			"img2":"images/shizijun_2.png",
			"img3":"images/shizijun_3.png",
			"img4":"images/shizijun_4.png"
			}
		]},
		{"duizhan":[
			{
				"title1":"剑术（主动）",
				"title2":"连击（被动）"
			},
			{
			"info1":"华丽的剑术，一次攻击造成3段伤害，每段伤害为普通攻击力的50%",
			"info2":"每对敌人造成6次伤害后就能额外攻击一次",
			"img5":"images/shizijun_5.png",
			"img6":"images/shizijun_6.png"
			}		
		]},
		{"juexing":[
			{
				"img":"images/roles_shizijun.png"				
			},
			{
				"imgOn":"images/roles_shizijun_on.png"
			}
		]}
	]
	}
	,
	{"roles":[
		{
			"rolesPic":"images/bimeng.png"
		},
		{
			"introduce":"images/part3_bimeng.png"
		},
		{"tafang":[
			{
				"title":[{"title1":"破坏（普攻）"},{"title2":"咆哮（被动）"},{"title3":"嗜血（小技能）"},{"title4":"愤怒（大技能）"}]
			},
			{
			"info1":"普通攻击，用巨大的双爪猛砸地面，对范围内的敌人造成物理伤害（激活天赋后）",
			"info2":"被动技能，触发概率和技能触发值有关，对敌人怒吼，对范围内的敌人造成物理伤害并眩晕1.5秒",
			"info3":"主动技能，一层能量满时可以释放，给范围内的友方增加攻击力",
			"info4":"主动技能，二层能量满时可以释放，愤怒的比蒙，对全屏范围内的所有敌人造成物理伤害",
			"img1":"images/bimeng_1.png",
			"img2":"images/bimeng_2.png",
			"img3":"images/bimeng_3.png",
			"img4":"images/bimeng_4.png"
			}
		]},
		{"duizhan":[
			{
				"title1":"撕裂（主动）",
				"title2":"利爪（被动）"
			},
			{
			"info1":"撕裂对手，并且使自身下一次攻击必定暴击",
			"info2":"攻击时忽视对方40%的护甲",
			"img5":"images/bimeng_5.png",
			"img6":"images/bimeng_6.png"
			}		
		]},
		{"juexing":[
			{
				"img":"images/roles_bimeng.png"				
			},
			{
				"imgOn":"images/roles_bimeng_on.png"
			}
		]}
	]
	}
	,
	{"roles":[
		{
			"rolesPic":"images/daemo.png"
		},
		{
			"introduce":"images/part3_daemo.png"
		},
		{"tafang":[
			{				
				"title":[{"title1":"收割（普攻）"},{"title2":"地狱收割（小技能）"},{"title3":"地狱送葬（大技能）"}]
			},
			{
			"info1":"普通攻击，挥舞镰刀攻击敌人，造成物理伤害",	
			"info2":"主动技能，一层能量满时可以释放，瞬移到目标附近，对单体耗费少量怒气造成大量魔法伤害",
			"info3":"主动技能，二层能量满时可以释放，来自地狱的召唤，对全屏的敌人造成大量魔法伤害",
			"img1":"images/daemo_1.png",
			"img2":"images/daemo_2.png",
			"img3":"images/daemo_3.png"
			}
		]},
		{"duizhan":[
			{
				"title1":"挑衅（主动）",
				"title2":"恶魔之体（被动）"
			},
			{
			"info1":"激怒敌人，使对方只能普攻，同时增加敌人的攻击力10%，降低命中40%",
			"info2":"每受到一次伤害，闪避值增加8，攻击力增加2%",
			"img5":"images/daemo_5.png",
			"img6":"images/daemo_6.png"
			}		
		]},
		{"juexing":[
			{
				"img":"images/roles_daemo.png"				
			},
			{
				"imgOn":"images/roles_daemo_on.png"
			}
		]}
	]
	}
	,
	{"roles":[
		{
			"rolesPic":"images/dafashi.png"
		},
		{
			"introduce":"images/part3_dafashi.png"
		},
		{"tafang":[
			{
				"title":[{"title1":"闪电追踪（普攻）"},{"title2":"水晶墙（小技能）"},{"title3":"星肖旋转（大技能）"}]
			},
			{
			"info1":"普通攻击，锁定敌人，造成持续的法术伤害",	
			"info2":"主动技能，一层能量满时可以释放，阻挡敌人的去路",
			"info3":"主动技能，二层能量满时可以释放，召唤时空之门，使进入的敌人回到起点",
			"img1":"images/dafashi_1.png",
			"img2":"images/dafashi_2.png",
			"img3":"images/dafashi_3.png"
			}
		]},
		{"duizhan":[
			{
				"title1":"急冻领域（主动）",
				"title2":"法力无边（被动）"
			},
			{
			"info1":"冰冻住对方，大大降低对方的攻速，攻速降低20%，持续5回合",
			"info2":"开场时释放全体buff，给敌我双方增加技能触发率",
			"img5":"images/dafashi_5.png",
			"img6":"images/dafashi_6.png"
			}		
		]},
		{"juexing":[
			{
				"img":"images/roles_dafashi.png"				
			}
		]}
	]
	}
	,
	{"roles":[
		{
			"rolesPic":"images/diyuquan.png"
		},
		{
			"introduce":"images/part3_diyuquan.png"
		},
		{"tafang":[
			{
				"title":[{"title1":"撕咬（普攻）"},{"title2":"地狱烈焰（被动）"},{"title3":"怒吼（小技能）"},{"title4":"狂化（大技能）"}]
			},
			{
			"info1":"普通攻击，撕咬，攻击目标敌人，造成单体物理伤害",
			"info2":"被动技能，触发概率和技能触发值有关，口吐烈焰攻击范围内的敌人，造成群体物理伤害",
			"info3":"主动技能，一层能量满时可以释放，怒吼对周围敌人造成群体物理伤害并减速",
			"info4":"主动技能，二层能量满时可以释放，狂化，提升自身大量攻击力",
			"img1":"images/diyuquan_1.png",
			"img2":"images/diyuquan_2.png",
			"img3":"images/diyuquan_3.png",
			"img4":"images/diyuquan_4.png"
			}
		]},
		{"duizhan":[
			{
				"title1":"饕餮之瞳（主动）",
				"title2":"凶狠撕咬（被动）"
			},
			{
			"info1":"造成120%伤害，并使对方攻击降低20%，持续1回合",
			"info2":"普通攻击额外造成一次40%攻击的伤害",
			"img5":"images/diyuquan_5.png",
			"img6":"images/diyuquan_6.png"
			}		
		]},
		{"juexing":[
			{
				"img":"images/roles_diyuquan.png"				
			}
		]}
	]
	}
	,
	{"roles":[
		{
			"rolesPic":"images/dulong.png"
		},
		{
			"introduce":"images/part3_dulong.png"
		},
		{"tafang":[
			{
				"title":[{"title1":"挥击（普攻）"},{"title2":"愤怒一击（被动）"},{"title3":"猛毒风暴（小技能）"},{"title4":"剧毒新星（大技能）"}]
			},
			{
			"info1":"普通攻击，使用攻击敌人，对单个敌人造成物理伤害",
			"info2":"被动技能，触发概率和技能触发值有关，跳起猛击地面攻击敌人，对自身周围的敌人造成物理伤害",
			"info3":"主动技能，一层能量满时可以释放，召唤猛毒风暴对直线范围内的敌人造成魔法攻击",
			"info4":"主动技能，二层能量满时可以释放，召唤剧毒新星，对全屏的敌人造成魔法伤害并中毒",
			"img1":"images/dulong_1.png",
			"img2":"images/dulong_2.png",
			"img3":"images/dulong_3.png",
			"img4":"images/dulong_4.png"
			}
		]},
		{"duizhan":[
			{
				"title1":"愤怒爪击（主动）",
				"title2":"浴血屠戮（被动）"
			},
			{
			"info1":"造成120%伤害，提升自身50%暴击率，持续2回合",
			"info2":"暴击时回复此次攻击100%数值的生命值",
			"img5":"images/dulong_5.png",
			"img6":"images/dulong_6.png"
			}		
		]},
		{"juexing":[
			{
				"img":"images/roles_dulong.png"				
			}
		]}
	]
	}
	,
	{"roles":[
		{
			"rolesPic":"images/dujiaoshou.png"
		},
		{
			"introduce":"images/part3_dujiaoshou.png"
		},
		{"tafang":[
			{
				"title":[{"title1":"召唤旋风（普攻）"},{"title2":"魔力环绕（被动）"},{"title3":"暴风雪（小技能）"},{"title4":"星耀闪光（大技能）"}]
			},
			{
			"info1":"普通攻击，挥舞法杖召唤旋风攻击敌人，造成范围魔法伤害，造成减速效果",
			"info2":"被动技能，触发概率和技能触发值有关，向森林之神祈祷，释放强大的魔法阵攻击周围的敌人",
			"info3":"主动技能，一层能量满时可以释放，旋转法杖释放暴风雪，攻击范围内的所有敌人，造成群体魔法伤害",
			"info4":"主动技能，二层能量满时可以释放，向森林之神祈祷，释放强大的魔法闪光致盲自身周围的敌人，造成魔法伤害",
			"img1":"images/dujiaoshou_1.png",
			"img2":"images/dujiaoshou_2.png",
			"img3":"images/dujiaoshou_3.png",
			"img4":"images/dujiaoshou_4.png"
			}
		]},
		{"duizhan":[
			{
				"title1":"精灵之光（主动）",
				"title2":"精灵印记（被动）"
			},
			{
			"info1":"造成伤害，并降低敌方命中，持续3回合",
			"info2":"独角兽死亡后留下精灵印记，提升技能触发500点，持续3回合",
			"img5":"images/dujiaoshou_5.png",
			"img6":"images/dujiaoshou_6.png"
			}		
		]},
		{"juexing":[
			{
				"img":"images/roles_dujiaoshou.png"				
			}
		]}
	]
	}
	,
	{"roles":[
		{
			"rolesPic":"images/duyanjuren.png"
		},
		{
			"introduce":"images/part3_duyanjuren.png"
		},
		{"tafang":[
			{
				"title":[{"title1":"投掷石块（普攻）"},{"title2":"燃烧滚石（小技能）"},{"title3":"陨石爆轰（大技能）"}]
			},
			{
			"info1":"普通攻击，丢出手上的石块，对目标敌人造成物理伤害",
			"info2":"主动技能，一层能量满时可以释放，投出燃烧着的石头，对直线上的所有敌人造成物理伤害",
			"info3":"主动技能，二层能量满时可以释放，投出巨大的石块，对范围内的所有敌人造成物理伤害和眩晕效果",
			"img1":"images/duyanjuren_1.png",
			"img2":"images/duyanjuren_2.png",
			"img3":"images/duyanjuren_3.png",
			"img4":"images/duyanjuren_4.png"
			}
		]},
		{"duizhan":[
			{
				"title1":"投石（主动）",
				"title2":"重击（被动）"
			},
			{
			"info1":"立刻造成125%伤害，3回合后目标再次受到同样伤害",
			"info2":"20%几率击晕目标",
			"img5":"images/duyanjuren_5.png",
			"img6":"images/duyanjuren_6.png"
			}		
		]},
		{"juexing":[
			{
				"img":"images/roles_duyanjuren.png"				
			}
		]}
	]
	}
	,
	{"roles":[
		{
			"rolesPic":"images/fenghuang.png"
		},
		{
			"introduce":"images/part3_fenghuang.png"
		},
		{"tafang":[
			{
				"title":[{"title1":"火焰流星（普攻）"},{"title2":"火焰之心（被动）"},{"title3":"烈焰风暴（小技能）"},{"title4":"焰之怒（大技能）"}]
			},
			{
			"info1":"普通攻击，召唤火焰流星攻击敌人，对范围内的敌人造成魔法伤害（激活天赋后）",
			"info2":"被动技能，触发概率和技能触发值有关，召唤火焰旋风攻击敌人，对范围内的敌人造成2段魔法伤害",
			"info3":"主动技能，一层能量满时可以释放，召唤烈焰风暴对范围内的敌人造成魔法伤害",
			"info4":"主动技能，二层能量满时可以释放，召唤大量火焰流星，对全屏的敌人造成7段魔法伤害",
			"img1":"images/fenghuang_1.png",
			"img2":"images/fenghuang_2.png",
			"img3":"images/fenghuang_3.png",
			"img4":"images/fenghuang_4.png"
			}
		]},
		{"duizhan":[
			{
				"title1":"烈火神盾（主动）",
				"title2":"浴火重生（被动）"
			},
			{
			"info1":"给自己施加火盾，被近战攻击会反弹，反弹伤害与自身攻击力的50%，有火盾状态下会根据火盾剩余次数触发重生",
			"info2":"死亡时如果有烈火神盾则复活，复活后的血量由烈火神盾剩余次数决定，每一层火盾可恢复10%的血量",
			"img5":"images/fenghuang_5.png",
			"img6":"images/fenghuang_6.png"
			}		
		]},
		{"juexing":[
			{
				"img":"images/roles_fenghuang.png"				
			}
		]}
	]
	}
	,
	{"roles":[
		{
			"rolesPic":"images/gelu.png"
		},
		{
			"introduce":"images/part3_gelu.png"
		},
		{"tafang":[
			{
				"title":[{"title1":"射击（普攻）"},{"title2":"心神凝聚（小技能）"},{"title3":"火力全开（大技能）"}]
			},
			{
			"info1":"普通攻击，射击，对单个敌人造成物理伤害",
			"info2":"主动技能，一层能量满时可以释放，大幅提升自身攻击力与攻击速度",
			"info3":"主动技能，二层能量满时可以释放，向前方连续射击，对直线范围内目标造成大量物理伤害",
			"img1":"images/gelu_1.png",
			"img2":"images/gelu_2.png",
			"img3":"images/gelu_3.png",
			"img4":"images/gelu_4.png"
			}
		]},
		{"duizhan":[
			{
				"title1":"集中火力（主动）",
				"title2":"穿透箭（被动）"
			},
			{
			"info1":"提升自身100%攻击速度，持续3回合",
			"info2":"攻击时忽视对方50%的护甲",
			"img5":"images/gelu_5.png",
			"img6":"images/gelu_6.png"
			}		
		]},
		{"juexing":[
			{
				"img":"images/roles_gelu.png"				
			}
		]}
	]
	}
	,
	{"roles":[
		{
			"rolesPic":"images/huojingling.png"
		},
		{
			"introduce":"images/part3_huojingling.png"
		},
		{"tafang":[
			{
				"title":[{"title1":"火球（普攻）"},{"title2":"余烬领域（小技能）"},{"title3":"熔岩地狱（大技能）"}]
			},
			{
			"info1":"普通攻击，发射小火球攻击敌人，造成单体魔法伤害",
			"info2":"主动技能，一层能量满时可以释放，释放火焰领域，对范围内的敌人造成魔法伤害",
			"info3":"主动技能，二层能量满时可以释放，召唤地狱入口，对范围内的敌人造成大量魔法伤害和眩晕效果",
			"img1":"images/huojingling_1.png",
			"img2":"images/huojingling_2.png",
			"img3":"images/huojingling_3.png",
			"img4":"images/huojingling_4.png"
			}
		]},
		{"duizhan":[
			{
				"title1":"燃烧（主动）",
				"title2":"点燃（被动）"
			},
			{
			"info1":"主动技能将会一次性引燃目标身上的所有点燃效果（清除点燃效果），基础伤害150%，每层点燃提高伤害35%",
			"info2":"普通攻击会点燃目标，使其受到伤害提高10%，持续3回合，最多5层",
			"img5":"images/huojingling_5.png",
			"img6":"images/huojingling_6.png"
			}		
		]},
		{"juexing":[
			{
				"img":"images/roles_huojingling.png"				
			}
		]}
	]
	}
	,
	{"roles":[
		{
			"rolesPic":"images/jisi.png"
		},
		{
			"introduce":"images/part3_jisi.png"
		},
		{"tafang":[
			{
				"title":[{"title1":"能量攻击（普攻）"},{"title2":"能量投放（被动）"},{"title3":"能量爆发（小技能）"},{"title4":"（大技能）"}]
			},
			{
			"info1":"普通攻击，将能量球聚集成球状发射出去，造成魔法伤害",
			"info2":"被动技能，触发概率和技能触发值有关，将能量聚集成球状投掷出去，对直线上的敌人造成魔法伤害",
			"info3":"主动技能，一层能量满时可以释放，将能量聚集在一起后爆开，对自身周围的所有敌人造成魔法伤害",
			"info4":"主动技能，二层能量满时可以释放，操控多个能量球围着施法者逐渐向外旋转出去，造成魔法伤害",
			"img1":"images/jisi_1.png",
			"img2":"images/jisi_2.png",
			"img3":"images/jisi_3.png",
			"img4":"images/jisi_4.png"
			}
		]},
		{"duizhan":[
			{
				"title1":"祈祷（主动）",
				"title2":"驱散（被动）"
			},
			{
			"info1":"回复大量生命值",
			"info2":"普通攻击时，驱散对方有益buff，如果没有buff则提升本次攻击的伤害10%",
			"img5":"images/jisi_5.png",
			"img6":"images/jisi_6.png"
			}		
		]},
		{"juexing":[
			{
				"img":"images/roles_jisi.png"				
			}
		]}
	]
	}
	,
	{"roles":[
		{
			"rolesPic":"images/jinlong.png"
		},
		{
			"introduce":"images/part3_jinlong.png"
		},
		{"tafang":[
			{
				"title":[{"title1":"火焰吐息（普攻）"},{"title2":"爆炎吐息（被动）"},{"title3":"烈焰飞行（小技能）"},{"title4":"末日浩劫（大技能）"}]
			},
			{
			"info1":"普通攻击，喷吐火焰攻击前方范围内所有目标，造成魔法伤害",
			"info2":"被动技能，触发概率和技能触发值有关，持续喷吐火焰，攻击前方范围内所有目标，造成魔法伤害",
			"info3":"主动技能，一层能量满时可以释放，飞出屏幕后从天上喷出火焰，对屏幕任意一直线范围内造成魔法伤害",
			"info4":"主动技能，二层能量满时可以释放，聚集魔力使地面中喷射出熔岩，对全屏目标造成魔法伤害",
			"img1":"images/jinlong_1.png",
			"img2":"images/jinlong_2.png",
			"img3":"images/jinlong_3.png",
			"img4":"images/jinlong_4.png"
			}
		]},
		{"duizhan":[
			{
				"title1":"黄金之城（主动）",
				"title2":"神圣鳞甲（被动）"
			},
			{
			"info1":"对目标造成120%伤害，并制造黄金城环境（持续10回合）：受到伤害降低，降低数值为黄金龙攻击力的16%",
			"info2":"每次被攻击时，回复16%黄金龙自身攻击力的血量",
			"img5":"images/jinlong_5.png",
			"img6":"images/jinlong_6.png"
			}		
		]},
		{"juexing":[
			{
				"img":"images/roles_jinlong.png"				
			}
		]}
	]
	}
	,
	{"roles":[
		{
			"rolesPic":"images/jinglinglieshou.png"
		},
		{
			"introduce":"images/part3_jinglingsheshou.png"
		},
		{"tafang":[
			{
				"title":[{"title1":"射击（普攻）"},{"title2":"二连射（被动）"},{"title3":"多重散射（小技能）"},{"title4":"穿云箭雨（大技能）"}]
			},
			{
			"info1":"普通攻击，发射弓箭攻击敌人，造成物理伤害",
			"info2":"被动技能，触发概率和技能触发值有关，连续射出2箭，对单个敌人造成200%的物理伤害",
			"info3":"主动技能，一层能量满时可以释放，连续射出多支箭，对范围内的敌人造成物理伤害",
			"info4":"主动技能，二层能量满时可以释放，连续射出多支箭后蓄气射出穿云箭，对范围内的所有敌人造成大量物理伤害",
			"img1":"images/jinglinglieshou_1.png",
			"img2":"images/jinglinglieshou_2.png",
			"img3":"images/jinglinglieshou_3.png",
			"img4":"images/jinglinglieshou_4.png"
			}
		]},
		{"duizhan":[
			{
				"title1":"精灵连击（主动）",
				"title2":"射击调整（被动）"
			},
			{
			"info1":"造成120%伤害，并施加debuff：使受到的技能的伤害提高30%，持续3回合，可叠加，无上限",
			"info2":"普通攻击命中敌人时，增加自己30点技能触发，持续1回合，可叠加，无上限",
			"img5":"images/jinglinglieshou_5.png",
			"img6":"images/jinglinglieshou_6.png"
			}		
		]},
		{"juexing":[
			{
				"img":"images/roles_jinglingsheshou.png"				
			},
			{
				"imgOn":"images/roles_jinglingsheshou_on.png"
			}
		]}
	]
	}
	,
	{"roles":[
		{
			"rolesPic":"images/leiliao.png"
		},
		{
			"introduce":"images/part3_leiliao.png"
		},
		{"tafang":[
			{
				"title":[{"title1":"爪击（普攻）"},{"title2":"闪电镣铐（小技能）"},{"title3":"雷云风暴（大技能）"}]
			},
			{
			"info1":"普通攻击，用嘴啄，对目标敌人造成魔法伤害",
			"info2":"主动技能，一层能量满时可以释放，锁定单个目标，对单个目标造成持续压制和魔法伤害",
			"info3":"主动技能，二层能量满时可以释放，召唤天雷攻击大范围目标，造成魔法伤害",
			"img1":"images/leiliao_1.png",
			"img2":"images/leiliao_2.png",
			"img3":"images/leiliao_3.png",
			"img4":"images/leiliao_4.png"
			}
		]},
		{"duizhan":[
			{
				"title1":"迅捷爪击（主动）",
				"title2":"落雷（被动）"
			},
			{
			"info1":"一次攻击造成2次伤害，每段伤害为25%，提升自身攻速50%，持续2回合",
			"info2":"每造成7次伤害时触发落雷，对敌方造成100%伤害并眩晕1回合",
			"img5":"images/leiliao_5.png",
			"img6":"images/leiliao_6.png"
			}		
		]},
		{"juexing":[
			{
				"img":"images/roles_leiliao.png"				
			}
		]}
	]
	}
	,
	{"roles":[
		{
			"rolesPic":"images/airen.png"
		},
		{
			"introduce":"images/part3_airen.png"
		},
		{"tafang":[
			{
				"title":[{"title1":"锤击（普攻）"},{"title2":"回转之锤（被动）"},{"title3":"爆炸飞锤（小技能）"},{"title4":"强袭飞锤（大技能）"}]
			},
			{
			"info1":"普通攻击，快速的挥动战锤，造成物理伤害",
			"info2":"被动技能，触发概率和技能触发值有关，将手中的战锤投掷出去，对沿途的敌人造成物理伤害",
			"info3":"主动技能，一层能量满时可以释放，将能量聚集在战锤上投掷出去，对范围内的敌人造成物理伤害",
			"info4":"主动技能，二层能量满时可以释放，将能量聚集在战锤上投掷出去，对范围内的敌人造成大量物理伤害",
			"img1":"images/airen_1.png",
			"img2":"images/airen_2.png",
			"img3":"images/airen_3.png",
			"img4":"images/airen_4.png"
			}
		]},
		{"duizhan":[
			{
				"title1":"藏宝大师（主动）",
				"title2":"石质体魄（被动）"
			},
			{
			"info1":"对目标造成伤害，并偷取一个buff，加到随机队友身上",
			"info2":"免疫所有buff与debuff",
			"img5":"images/airen_5.png",
			"img6":"images/airen_6.png"
			}		
		]},
		{"juexing":[
			{
				"img":"images/roles-airen.png"				
			}
		]}
	]
	}
	,
	{"roles":[
		{
			"rolesPic":"images/meidush.png"
		},
		{
			"introduce":"images/part3_meidusha.png"
		},
		{"tafang":[
			{
				"title":[{"title1":"射击（普攻）"},{"title2":"毒液喷射（被动）"},{"title3":"石化光线（小技能）"},{"title4":"美杜莎之眼（大技能）"}]
			},
			{
			"info1":"普通攻击，射出箭矢，对敌人造成物理伤害",
			"info2":"被动技能，触发概率和技能触发值有关，对范围内的敌人造成魔法伤害",
			"info3":"主动技能，一层能量满时可以释放，对范围内的敌人造成魔法伤害，并眩晕2秒",
			"info4":"主动技能，二层能量满时可以释放，美杜莎睁开石化之眼，定住全屏范围内的敌人2秒",
			"img1":"images/meidusha_1.png",
			"img2":"images/meidusha_2.png",
			"img3":"images/meidusha_3.png",
			"img4":"images/meidusha_4.png"
			}
		]},
		{"duizhan":[
			{
				"title1":"石化（主动）",
				"title2":"毒性攻击（被动）"
			},
			{
			"info1":"石化目标，使目标无法行动1回合，同时提高目标防御150%，无法连续生效",
			"info2":"普通攻击使对方中毒，每回合失去200点体力",
			"img5":"images/meidusha_5.png",
			"img6":"images/meidusha_6.png"
			}		
		]},
		{"juexing":[
			{
				"img":"images/roles_meidusha.png"				
			},
			{
				"imgOn":"images/roles_meidusha_on.png"
			}
		]}
	]
	}
	,
	{"roles":[
		{
			"rolesPic":"images/niutou.png"
		},
		{
			"introduce":"images/part3_niutou.png"
		},
		{"tafang":[
			{
				"title":[{"title1":"牛头强袭（普攻）"},{"title2":"战争践踏（小技能）"},{"title3":"牛头人之怒（大技能）"}]
			},
			{
			"info1":"普通攻击，使用手上的巨斧挥砍敌人，造成物理伤害",
			"info2":"主动技能，一层能量满时可以释放，猛踩地面，对以自身为半径的范围内敌人造成物理伤害并眩晕",
			"info3":"主动技能，二层能量满时可以释放，牛头人愤怒的一击，对以自身为半径的范围内敌人造成2次物理伤害",
			"img1":"images/niutou_1.png",
			"img2":"images/niutou_2.png",
			"img3":"images/niutou_3.png",
			"img4":"images/niutou_4.png"
			}
		]},
		{"duizhan":[
			{
				"title1":"狂怒（主动）",
				"title2":"勇猛（被动）"
			},
			{
			"info1":"提升攻击50%，降低防御35%，并清除自身debuff",
			"info2":"血量低于30%时，可造成180%伤害",
			"img5":"images/niutou_5.png",
			"img6":"images/niutou_6.png"
			}		
		]},
		{"juexing":[
			{
				"img":"images/roles_niutou.png"				
			},
			{
				"imgOn":"images/roles_niutou_on.png"
			}
		]}
	]
	}
	,
	{"roles":[
		{
			"rolesPic":"images/nvshou.png"
		},
		{
			"introduce":"images/part3_nvshou.png"
		},
		{"tafang":[
			{
				"title":[{"title1":"射击（普攻）"},{"title2":"重弩射击（被动）"},{"title3":"石化光线（小技能）"},{"title4":"美杜莎之眼（大技能）"}]
			},
			{
			"info1":"普通攻击，发射弩箭攻击敌人，对敌人造成物理伤害",
			"info2":"被动技能，触发概率和技能触发值有关，使用重型弩箭攻击敌人，造成较大物理伤害，并使其眩晕",
			"info3":"主动技能，一层能量满时可以释放，对范围内的敌人造成魔法伤害，并眩晕2秒",
			"info4":"主动技能，二层能量满时可以释放，美杜莎睁开石化之眼，定住全屏范围内的敌人2秒",
			"img1":"images/nvshou_1.png",
			"img2":"images/nvshou_2.png",
			"img3":"images/nvshou_3.png",
			"img4":"images/nvshou_4.png"
			}
		]},
		{"duizhan":[
			{
				"title1":"精准射击（主动）",
				"title2":"破甲（被动）"
			},
			{
			"info1":"精准的射击造成伤害，同时提高自身命中值50%",
			"info2":"攻击的同时破坏敌人的护甲，降低对手的防御力60%",
			"img5":"images/nvshou_5.png",
			"img6":"images/nvshou_6.png"
			}		
		]},
		{"juexing":[
			{
				"img":"images/roles_nvshou.png"				
			},
			{
				"imgOn":"images/roles_nvshou_on.png"
			}
		]}
	]
	}
	,
	{"roles":[
		{
			"rolesPic":"images/oke.png"
		},
		{
			"introduce":"images/part3_oke.png"
		},
		{"tafang":[
			{
				"title":[{"title1":"图腾打击（普攻）"},{"title2":"撼地打击（被动）"},{"title3":"嗜血奇术（小技能）"},{"title4":"嗜血狂暴（大技能）"}]
			},
			{
			"info1":"普通攻击，挥击手中的图腾，对目标敌人造成物理伤害",
			"info2":"被动技能，触发概率和技能触发值有关，用手中的武器猛击地面，造成范围物理伤害",
			"info3":"主动技能，一层能量满时可以释放，对单个友军释放嗜血术，增加大量攻击力",
			"info4":"主动技能，二层能量满时可以释放，给范围内的友方目标增加大量攻击力与200怒气",
			"img1":"images/oke_1.png",
			"img2":"images/oke_2.png",
			"img3":"images/oke_3.png",
			"img4":"images/oke_4.png"
			}
		]},
		{"duizhan":[
			{
				"title1":"怒吼（主动）",
				"title2":"斩杀（被动）"
			},
			{
			"info1":"给己方所有人增加8%攻击力，可无限叠加",
			"info2":"对生命低于30%的目标造成100%额外伤害",
			"img5":"images/oke_5.png",
			"img6":"images/oke_6.png"
			}		
		]},
		{"juexing":[
			{
				"img":"images/roles_oke.png"				
			}
		]}
	]
	}
	,
	{"roles":[
		{
			"rolesPic":"images/renleiqishi.png"
		},
		{
			"introduce":"images/part3_renleiqishi.png"
		},
		{"tafang":[
			{
				"title":[{"title1":"突刺（普攻）"},{"title2":"重击（被动）"},{"title3":"冲刺（小技能）"},{"title4":"冠军冲锋（大技能）"}]
			},
			{
			"info1":"普通攻击，对敌人造成物理伤害",
			"info2":"被动技能，触发概率和技能触发值有关，对单个敌人造成200%的物理伤害",
			"info3":"主动技能，一层能量满时可以释放，对屏幕任意一直线范围内的敌人造成物理伤害并击飞",
			"info4":"主动技能，二层能量满时可以释放，对屏幕任意一直线范围内的敌人造成大量物理伤害",
			"img1":"images/renleiqishi_1.png",
			"img2":"images/renleiqishi_2.png",
			"img3":"images/renleiqishi_3.png",
			"img4":"images/renleiqishi_4.png"
			}
		]},
		{"duizhan":[
			{
				"title1":"蓄势待发（主动）",
				"title2":"骑士精神（）"
			},
			{
			"info1":"做冲锋准备，防御力增加100%，并提高下一回个的攻击力和命中100%，持续1回合",
			"info2":"死亡后给己方其他人增加攻击力10%，所有伙伴共享12回合",
			"img5":"images/renleiqishi_4.png",
			"img6":"images/renleiqishi_3.png"
			}		
		]},
		{"juexing":[
			{
				"img":"images/roles_qishi.png"				
			}
		]}
	]
	}
	,
	{"roles":[
		{
			"rolesPic":"images/sangdeluo.png"
		},
		{
			"introduce":"images/part3_sangdeluo.png"
		},
		{"tafang":[
			{
				"title":[{"title1":"骸骨利爪（普攻）"},{"title2":"幽冥突刺（小技能）"},{"title3":"冥府之握（大技能）"}]
			},
			{
			"info1":"普通攻击，爪击，对单个敌人造成物理伤害",
			"info2":"主动技能，一层能量满时可以释放，对单个敌人释放骨矛，造成巨大的物理伤害并击飞",
			"info3":"主动技能，二层能量满时可以释放，召唤冥界的骨爪形成监牢，能同时攻击目标周围的敌人，造成巨大的物理伤害并眩晕",
			"img1":"images/sangdeluo_1.png",
			"img2":"images/sangdeluo_2.png",
			"img3":"images/sangdeluo_3.png",
			"img4":"images/sangdeluo_4.png"
			}
		]},
		{"duizhan":[
			{
				"title1":"死亡之爪（主动）",
				"title2":"骨墙（被动）"
			},
			{
			"info1":"造成120%伤害，并降低敌方攻击力300点，持续3回合",
			"info2":"每当受到攻击时，提高自身50%防御和攻击持续1回合",
			"img5":"images/sangdeluo_5.png",
			"img6":"images/sangdeluo_6.png"
			}		
		]},
		{"juexing":[
			{
				"img":"images/roles_shangdeluo.png"				
			}
		]}
	]
	}
	,
	{"roles":[
		{
			"rolesPic":"images/shenv.png"
		},
		{
			"introduce":"images/part3_shenv.png"
		},
		{"tafang":[
			{
				"title":[{"title1":"二连斩（普攻）"},{"title2":"回旋剑舞（小技能）"},{"title3":"疯狂屠戮（大技能）"}]
			},
			{
			"info1":"普通攻击，交替挥舞双剑，对目标敌人造成2次物理伤害",
			"info2":"主动技能，一层能量满时可以释放，快速旋转对自身周围目标造成多段物理伤害",
			"info3":"主动技能，二层能量满时可以释放，在战场上来回穿梭，对全屏目标造成多段物理伤害",
			"img1":"images/shenv_1.png",
			"img2":"images/shenv_2.png",
			"img3":"images/shenv_3.png",
			"img4":"images/shenv_4.png"
			}
		]},
		{"duizhan":[
			{
				"title1":"灵蛇剑舞（主动）",
				"title2":"优雅蛇躯（被动）"
			},
			{
			"info1":"华丽的十字斩，一次攻击造成4段伤害，每段伤害为普通攻击力的30%",
			"info2":"每次造成伤害时使自己的速度永久提高5%，最多可叠加20层",
			"img5":"images/shenv_5.png",
			"img6":"images/shenv_6.png"
			}		
		]},
		{"juexing":[
			{
				"img":"images/roles_shenv.png"				
			}
		]}
	]
	}
	,
	{"roles":[
		{
			"rolesPic":"images/shenguai.png"
		},
		{
			"introduce":"images/part3_shenguai.png"
		},
		{"tafang":[
			{
				"title":[{"title1":"能量电球（普攻）"},{"title2":"霹雳闪电（被动）"},{"title3":"神圣赐福（小技能）"},{"title4":"圣灵祈愿（大技能）"}]
			},
			{
			"info1":"普通攻击，锁定敌人，造成持续的法术伤害",
			"info2":"被动技能，触发概率和技能触发值有关，召唤雷霆攻击范围内的敌人，造成魔法伤害",
			"info3":"主动技能，一层能量满时可以释放，给指定的友方目标增加技能触发率与攻击速度",
			"info4":"主动技能，二层能量满时可以释放，给范围内的友方目标增加技能触发率与攻击速度",
			"img1":"images/shenguai_1.png",
			"img2":"images/shenguai_2.png",
			"img3":"images/shenguai_3.png",
			"img4":"images/shenguai_4.png"
			}
		]},
		{"duizhan":[
			{
				"title1":"元素操控（主动）",
				"title2":"迅捷祝福（被动）"
			},
			{
			"info1":"对目标造成135%伤害，同时复制自己身上的debuff到目标身上",
			"info2":"神怪死亡后释放祝福，提升速度100%，持续4回合",
			"img5":"images/shenguai_5.png",
			"img6":"images/shenguai_6.png"
			}		
		]},
		{"juexing":[
			{
				"img":"images/roles_shenguai.png"				
			}
		]}
	]
	}
	,
	{"roles":[
		{
			"rolesPic":"images/shiwu.png"
		},
		{
			"introduce":"images/part3_shiwu.png"
		},
		{"tafang":[
			{
				"title":[{"title1":"鬼魂（普攻）"},{"title2":"双生怨灵（被动）"},{"title3":"地狱咆哮（小技能）"},{"title4":"亡灵大军（大技能）"}]
			},
			{
			"info1":"普通攻击，召唤鬼魂攻击敌人，对敌人造成魔法伤害",
			"info2":"被动技能，触发概率和技能触发值有关，召唤2个怨灵攻击敌人，对敌人造成魔法伤害",
			"info3":"主动技能，一层能量满时可以释放，对范围内的敌人造成1次魔法伤害",
			"info4":"主动技能，二层能量满时可以释放，对范围内的敌人造成6次魔法伤害",
			"img1":"images/shiwu_1.png",
			"img2":"images/shiwu_2.png",
			"img3":"images/shiwu_3.png",
			"img4":"images/shiwu_4.png"
			}
		]},
		{"duizhan":[
			{
				"title1":"死亡之云（主动）",
				"title2":"尸毒天下（被动）"
			},
			{
			"info1":"释放死亡之云，造成伤害并使对方中毒，每回合失去体力，持续3回合",
			"info2":"死亡后使对方中毒，每回合失去10%最大血量（上限为尸巫攻击力的100%），持续4回合",
			"img5":"images/shiwu_5.png",
			"img6":"images/shiwu_6.png"
			}		
		]},
		{"juexing":[
			{
				"img":"images/roles_shiwu.png"				
			},
			{
				"imgOn":"images/roles_shiwu_on.png"
			}
		]}
	]
	}
	,
	{"roles":[
		{
			"rolesPic":"images/shijiu.png"
		},
		{
			"introduce":"images/part3_shijiu.png"
		},
		{"tafang":[
			{
				"title":[{"title1":"爪击（普攻）"},{"title2":"双爪击（被动）"},{"title3":"旋风（小技能）"},{"title4":"大旋风（大技能）"}]
			},
			{
			"info1":"普通攻击，挥动巨大的爪子攻击敌人，造成物理伤害",
			"info2":"被动技能，触发概率和技能触发值有关，挥动两个巨大的爪子击杀敌人，造成双倍的物理伤害",
			"info3":"主动技能，一层能量满时可以释放，挥动双臂造成强力的旋风，造成3次魔法伤害",
			"info4":"主动技能，二层能量满时可以释放，挥动双臂造成巨大的旋风，造成四次魔法伤害。并额外对旋风中心十字范围内的敌人造成魔法伤害",
			"img1":"images/shijiu_1.png",
			"img2":"images/shijiu_2.png",
			"img3":"images/shijiu_3.png",
			"img4":"images/shijiu_4.png"
			}
		]},
		{"duizhan":[
			{
				"title1":"旋风之力（主动）",
				"title2":"反击（被动）"
			},
			{
			"info1":"让对方感受旋风的力量，提高对手攻速25%并降低对手20%攻击力",
			"info2":"遇到近战攻击时可以反击，伤害为当前血量的12%",
			"img5":"images/shijiu_5.png",
			"img6":"images/shijiu_6.png"
			}		
		]},
		{"juexing":[
			{
				"img":"images/roles_shijiu.png"				
			},
			{
				"imgOn":"images/roles_shijiu_on.png"
			}
		]}
	]
	}
	,
	{"roles":[
		{
			"rolesPic":"images/shuren.png"
		},
		{
			"introduce":"images/part3_shuren.png"
		},
		{"tafang":[
			{
				"title":[{"title1":"捶击（普攻）"},{"title2":"大地震击（小技能）"},{"title3":"狂乱捶击（大技能）"}]
			},
			{
			"info1":"普通攻击，挥动拳头捶击敌人，造成物理伤害",
			"info2":"主动技能，一层能量满时可以释放，猛捶地面，对以自身为半径的范围内敌人造成物理伤害",
			"info3":"主动技能，二层能量满时可以释放，树精愤怒的连击，对以自身为半径的范围内敌人造成3次物理伤害",
			"img1":"images/shuren_1.png",
			"img2":"images/shuren_2.png",
			"img3":"images/shuren_3.png",
			"img4":"images/shuren_4.png"
			}
		]},
		{"duizhan":[
			{
				"title1":"自然之力（主动）",
				"title2":"寄生之种（被动）"
			},
			{
			"info1":"造成100%伤害，并随机附加debuff",
			"info2":"每次有人进场时，敌方都会眩晕一个回合，树人死亡后失效。（仅对生命值低于树人的目标失效）",
			"img5":"images/shuren_5.png",
			"img6":"images/shuren_6.png"
			}		
		]},
		{"juexing":[
			{
				"img":"images/roles_shuren.png"				
			},
			{
				"imgOn":"images/roles_shuren_on.png"
			}
		]}
	]
	}
	,
	{"roles":[
		{
			"rolesPic":"images/siwangqishi.png"
		},
		{
			"introduce":"images/part3_siqi.png"
		},
		{"tafang":[
			{
				"title":[{"title1":"剑气挥砍（普攻）"},{"title2":"十字星斩（被动）"},{"title3":"死亡之息（小技能）"},{"title4":"死亡领域（大技能）"}]
			},
			{
			"info1":"普通攻击，挥砍并发出一刀死气，对敌人造成物理伤害",
			"info2":"被动技能，触发概率和技能触发值有关，对单个敌人造成200%的物理伤害",
			"info3":"主动技能，一层能量满时可以释放，对范围内的敌人造成5次物理伤害",
			"info4":"主动技能，二层能量满时可以释放，对以自身为圆心的范围内敌人造成6次魔法伤害",
			"img1":"images/siwangqishi_1.png",
			"img2":"images/siwangqishi_2.png",
			"img3":"images/siwangqishi_3.png",
			"img4":"images/siwangqishi_4.png"
			}
		]},
		{"duizhan":[
			{
				"title1":"致命一击（主动）",
				"title2":"夺命一击（被动）"
			},
			{
			"info1":"攻击对面的致命位置，造成伤害并使对方重伤，下一次遭受的伤害增加60%",
			"info2":"10%的概率使用夺命一击，造成400%伤害",
			"img5":"images/siwangqishi_5.png",
			"img6":"images/siwangqishi_6.png"
			}		
		]},
		{"juexing":[
			{
				"img":"images/roles_siwangqishi.png"				
			}
		]}
	]
	}
	,
	{"roles":[
		{
			"rolesPic":"images/taitan.png"
		},
		{
			"introduce":"images/part3_taitan.png"
		},
		{"tafang":[
			{
				"title":[{"title1":"泰坦神箭（普攻）"},{"title2":"神罚之雷（被动）"},{"title3":"连锁闪电（小技能）"},{"title4":"雷霆风暴（大技能）"}]
			},
			{
			"info1":"普通攻击，从手上凝聚出泰坦神箭，攻击目标敌人，造成单体魔法伤害",
			"info2":"被动技能，触发概率和技能触发值有关，引导天雷审判范围内的敌人，造成群体魔法伤害",
			"info3":"主动技能，一层能量满时可以释放，释放在敌人间跳动的闪电链，造成群体魔法伤害",
			"info4":"主动技能，二层能量满时可以释放，在目标范围附近引导雷霆风暴，随机攻击范围内所有目标，造成群体魔法伤害",
			"img1":"images/taitan_1.png",
			"img2":"images/taitan_2.png",
			"img3":"images/taitan_3.png",
			"img4":"images/taitan_4.png"
			}
		]},
		{"duizhan":[
			{
				"title1":"神罚之力（主动）",
				"title2":"泰坦之力（被动）"
			},
			{
			"神罚之力（主动）":"对目标造成120%伤害，并制造雷电天气（持续8回合）：场上人每受到一次伤害，将引发一次神罚，受到一次普通伤害。（伤害计算防御减伤，泰坦对此伤害免疫）",
			"泰坦之力（被动）":"普通攻击额外造成一次35%攻击的伤害",
			"img5":"images/taitan_5.png",
			"img6":"images/taitan_6.png"
			}		
		]},
		{"juexing":[
			{
				"img":"images/roles_taitan.png"				
			},
			{
				"imgOn":"images/roles_taitan_on.png"
			}
		]}
	]
	}
	,
	{"roles":[
		{
			"rolesPic":"images/tianshi.png"
		},
		{
			"introduce":"images/part3_tianshi.png"
		},
		{"tafang":[
			{
				"title":[{"title1":"挥砍（普攻）"},{"title2":"天使之剑（小技能）"},{"title3":"神圣新星（大技能）"}]
			},
			{
			"info1":"普通攻击，挥出天使之剑，造成魔法伤害",
			"info2":"主动技能，一层能量满时可以释放，召唤天使之剑从天而降攻击敌人，对范围内的敌人造成大量魔法伤害",
			"info3":"主动技能，二层能量满时可以释放，将圣光集于剑端，然后释放出去，攻击所有的敌人，对全屏的敌人造成魔法伤害",
			"img1":"images/tianshi_1.png",
			"img2":"images/tianshi_2.png",
			"img3":"images/tianshi_3.png",
			"img4":"images/tianshi_4.png"
			}
		]},
		{"duizhan":[
			{
				"title1":"神圣复仇（主动）",
				"title2":"复活（被动）"
			},
			{
			"info1":"造成伤害，并返还受到积累伤害的15%，同时清空累积伤害",
			"info2":"20%概率死亡后恢复33%血量，全场一方只能生效一次",
			"img5":"images/tianshi_5.png",
			"img6":"images/tianshi_6.png"
			}		
		]},
		{"juexing":[
			{
				"img":"images/roles_tianshi.png"				
			},
			{
				"imgOn":"images/roles_tianshi_on.png"
			}
		]}
	]
	}
	,
	{"roles":[
		{
			"rolesPic":"images/xixiegui.png"
		},
		{
			"introduce":"images/part3_xixiegui.png"
		},
		{"tafang":[
			{
				"title":[{"title1":"蝙蝠攻击（普攻）"},{"title2":"渴血（被动）"},{"title3":"蝙蝠群（小技能）"},{"title4":"黑夜来临（大技能）"}]
			},
			{
			"info1":"普通攻击，命令蝙蝠攻击敌人，对敌人造成魔法伤害",
			"info2":"被动技能，触发概率和技能触发值有关，暴露本来面目，对着敌人猛咬一口，对多个敌人造成魔法伤害",
			"info3":"主动技能，一层能量满时可以释放，操控蝙蝠对着范围内的敌人持续攻击，对范围内的敌人造成3次魔法伤害",
			"info4":"主动技能，二层能量满时可以释放，化身于黑夜，大量蝙蝠横扫天空，对所有全屏的敌人造成6次魔法伤害",
			"img1":"images/xixiegui_1.png",
			"img2":"images/xixiegui_2.png",
			"img3":"images/xixiegui_3.png",
			"img4":"images/xixiegui_4.png"
			}
		]},
		{"duizhan":[
			{
				"title1":"魔力（主动）",
				"title2":"吸血（被动）"
			},
			{
			"info1":"造成伤害并降低对手防御力40%",
			"info2":"攻击附带30%吸血",
			"img5":"images/xixiegui_5.png",
			"img6":"images/xixiegui_6.png"
			}		
		]},
		{"juexing":[
			{
				"img":"images/roles_xixiegui.png"				
			},
			{
				"imgOn":"images/roles_xixiegui_on.png"
			}
		]}
	]
	}
	,
	{"roles":[
		{
			"rolesPic":"images/xiannvlong.png"
		},
		{
			"introduce":"images/part3_xiannvlong.png"
		},
		{"tafang":[
			{
				"title":[{"title1":"聚能法球（普攻）"},{"title2":"霹雳寒冰（被动）"},{"title3":"群体祈祷（小技能）"},{"title4":"星辰之怒（大技能）"}]
			},
			{
			"info1":"普通攻击，使用法球攻击敌人，对小范围敌人造成魔法伤害（激活天赋后）",
			"info2":"被动技能，触发概率和技能触发值有关，发出寒冰冲击，攻击范围内目标",
			"info3":"主动技能，一层能量满时可以释放，为范围内友方目标提升攻击速度并恢复怒气",
			"info4":"主动技能，二层能量满时可以释放，召唤星辰坠落，攻击全屏范围内目标",
			"img1":"images/xiannvlong_1.png",
			"img2":"images/xiannvlong_2.png",
			"img3":"images/xiannvlong_3.png",
			"img4":"images/xiannvlong_4.png"
			}
		]},
		{"duizhan":[
			{
				"title1":"龙语魔法（主动）",
				"title2":"无尽法力（被动）"
			},
			{
			"info1":"造成120%伤害，并对全队增加随机效果",
			"info2":"每回合都必定释放主动技能",
			"img5":"images/xiannvlong_5.png",
			"img6":"images/xiannvlong_6.png"
			}		
		]},
		{"juexing":[
			{
				"img":"images/roles_xiannvlong.png"				
			}
		]}
	]
	}
	,
	{"roles":[
		{
			"rolesPic":"images/xieshen.png"
		},
		{
			"introduce":"images/part3_xieshen.png"
		},
		{"tafang":[
			{
				"title":[{"title1":"炽热鞭挞（普攻）"},{"title2":"灵魂祭礼（小技能）"},{"title3":"邪神降临（大技能）"}]
			},
			{
			"info1":"普通攻击，鞭挞，攻击目标敌人，造成单体魔法伤害",
			"info2":"主动技能，一层能量满时可以释放，对敌人造成单体大量魔法伤害",
			"info3":"主动技能，二层能量满时可以释放，对敌人造成单体大量魔法伤害",
			"img1":"images/xieshen_1.png",
			"img2":"images/xieshen_2.png",
			"img3":"images/xieshen_3.png",
			"img4":"images/xieshen_4.png"
			}
		]},
		{"duizhan":[
			{
				"title1":"灵魂收割（主动）",
				"title2":"灵魂盛宴（被动）"
			},
			{
			"info1":"造成100%伤害，赐予自身一层灵魂之力",
			"info2":"登场时，根据已阵亡英雄总和，每名阵亡英雄赐予邪神一层灵魂之力，每层灵魂之力可提高7%攻击",
			"img5":"images/xieshen_5.png",
			"img6":"images/xieshen_6.png"
			}		
		]},
		{"juexing":[
			{
				"img":"images/roles_xieshen.png"				
			}
		]}
	]
	}
]

